fusion_engine-5.2.1.dist-info/METADATA
fusion_engine-5.2.1.dist-info/WHEEL
fusion_engine-5.2.1.dist-info/licenses/LICENSE.md
fusionengine/__init__.py
fusionengine/backend/deprecations.py
fusionengine/engine/animation.py
fusionengine/engine/color.py
fusionengine/engine/debug.py
fusionengine/engine/draw.py
fusionengine/engine/entity.py
fusionengine/engine/enums.py
fusionengine/engine/event.py
fusionengine/engine/exceptions.py
fusionengine/engine/image.py
fusionengine/engine/keys.py
fusionengine/engine/manager.py
fusionengine/engine/math.py
fusionengine/engine/node.py
fusionengine/engine/scene.py
fusionengine/engine/shape.py
fusionengine/engine/sound.py
fusionengine/engine/spritesheets.py
fusionengine/engine/storage.py
fusionengine/engine/ui.py
fusionengine/engine/vector.py
fusionengine/engine/window.py
fusionengine/examples/example1.py
fusionengine/examples/example2.py
fusionengine/examples/example3.py
fusionengine/examples/example4.py
fusionengine/examples/example5.py
fusionengine/external/fe.png
fusionengine/external/font.ttf
fusionengine/fusiongl/__init__.py
fusionengine/fusiongl/binding.py
fusionengine/fusiongl/libgl.py
fusion_engine-5.2.1.dist-info/RECORD
