Metadata-Version: 2.1
Name: fusion-engine
Version: 5.2.1
Summary: A custom open-source game engine on OpenGL and Python, it’s written in pure Python! It’s easy and fast!
Keywords: game python gamedev game-engine pygame game-development pure-python pygame-mixer pygame-ttf pygame-image python-game pygame-library python-game-library python-game-engine python-games
Author-Email: Dimkauzh <uzhdimka@gmail.com>
License: GNU GPLv3
Classifier: Development Status :: 5 - Production/Stable
Classifier: License :: OSI Approved :: GNU General Public License v3 (GPLv3)
Classifier: Natural Language :: English
Classifier: Operating System :: MacOS
Classifier: Operating System :: Microsoft :: Windows
Classifier: Operating System :: Unix
Classifier: Programming Language :: Python :: 3
Classifier: Programming Language :: Python :: 3 :: Only
Classifier: Programming Language :: Python :: 3.8
Classifier: Programming Language :: Python :: 3.9
Classifier: Programming Language :: Python :: 3.10
Classifier: Programming Language :: Python :: 3.11
Classifier: Programming Language :: Python :: 3.12
Classifier: Topic :: Games/Entertainment
Classifier: Topic :: Multimedia :: Graphics
Classifier: Topic :: Multimedia :: Video
Requires-Python: >=3.8
Requires-Dist: pygame-ce>=2.4.0
